vk_fetch/__init__.py
vk_fetch/commands/__init__.py
vk_fetch/commands/download.py
vk_fetch/commands/show.py
vk_fetch/constants.py
vk_fetch/core.py
vk_fetch/fetchers.py
vk_fetch/jobs/__init__.py
vk_fetch/jobs/base.py
vk_fetch/jobs/conversations.py
vk_fetch/jobs/photos.py
vk_fetch/jobs/profile.py
vk_fetch/logging.py
vk_fetch/models/__init__.py
vk_fetch/models/attachments.py
vk_fetch/models/conversations.py
vk_fetch/models/groups.py
vk_fetch/models/media_types/__init__.py
vk_fetch/models/media_types/audio.py
vk_fetch/models/media_types/media.py
vk_fetch/models/media_types/photo.py
vk_fetch/models/messages.py
vk_fetch/models/profile.py
vk_fetch/models/users.py
vk_fetch/run.py
vk_fetch/utils.py
vk_fetch-0.5.2.dist-info/entry_points.txt
vk_fetch-0.5.2.dist-info/LICENSE
vk_fetch-0.5.2.dist-info/METADATA
vk_fetch-0.5.2.dist-info/WHEEL
vk_fetch-0.5.2.dist-info/RECORD
