Metadata-Version: 2.1
Name: vk-fetch
Version: 0.5.2
Summary: Script helps to fetch all data from your VK account
Home-page: https://github.com/rmksrv/vk_fetch
License: MIT
Author: Roman Kosarev
Author-email: rmksrv@outlook.com
Requires-Python: >=3.11,<4.0
Classifier: License :: OSI Approved :: MIT License
Classifier: Programming Language :: Python :: 3
Classifier: Programming Language :: Python :: 3.11
Requires-Dist: loguru (>=0.6.0,<0.7.0)
Requires-Dist: python-dateutil (>=2.8.2,<3.0.0)
Requires-Dist: rich (>=13.3.1,<14.0.0)
Requires-Dist: typer[rich] (>=0.7.0,<0.8.0)
Requires-Dist: vk-api (>=11.9.9,<12.0.0)
